aas_http_client/__init__.py
aas_http_client/classes/Configuration/config_classes.py
aas_http_client/classes/client/aas_client.py
aas_http_client/classes/client/implementations/__init__.py
aas_http_client/classes/client/implementations/authentication.py
aas_http_client/classes/client/implementations/experimental_implementation.py
aas_http_client/classes/client/implementations/shell_implementation.py
aas_http_client/classes/client/implementations/shell_registry_implementation.py
aas_http_client/classes/client/implementations/sm_implementation.py
aas_http_client/classes/client/implementations/sm_registry_implementation.py
aas_http_client/classes/wrapper/attachment.py
aas_http_client/classes/wrapper/pagination.py
aas_http_client/classes/wrapper/sdk_wrapper.py
aas_http_client/demo/demo_process.py
aas_http_client/demo/logging_handler.py
aas_http_client/utilities/__init__.py
aas_http_client/utilities/encoder.py
aas_http_client/utilities/http_helper.py
aas_http_client/utilities/model_builder.py
aas_http_client/utilities/sdk_tools.py
aas_http_client/utilities/version_check.py
aas_http_client-0.9.4.dist-info/licenses/LICENSE
aas_http_client-0.9.4.dist-info/METADATA
aas_http_client-0.9.4.dist-info/WHEEL
aas_http_client-0.9.4.dist-info/top_level.txt
aas_http_client-0.9.4.dist-info/RECORD
