Metadata-Version: 2.4
Name: aas-http-client
Version: 0.9.4
Summary: Generic Python HTTP client for communication with various types of AAS servers
Author-email: Daniel Klein <daniel.klein@em.ag>
License: MIT License
Project-URL: Homepage, https://github.com/fluid40/aas-http-client
Requires-Python: >=3.11
License-File: LICENSE
Requires-Dist: pydantic>=2.12.5
Requires-Dist: requests>=2.32.5
Requires-Dist: basyx-python-sdk>=2.0.0
Requires-Dist: puremagic>=1.30
Dynamic: license-file
